{
  "platform": "react",
  "code": {
    "lang": "js",
    "scheme": "blackbox"
  },
  "style": {
    "scheme": "css-modules",
    "defaultStyleCssFilePath": ""
  },
  "images": {
    "scheme": "public-files",
    "publicDir": "../../public",
    "publicUrlPrefix": "/static/"
  },
  "tokens": {
    "scheme": "theo",
    "tokensFilePath": "plasmic-tokens.theo.json"
  },
  "srcDir": "src/components",
  "defaultPlasmicDir": "./plasmic",
  "projects": [],
  "globalVariants": {
    "variantGroups": []
  },
  "cliVersion": "0.1.107",
  "$schema": "https://unpkg.com/@plasmicapp/cli@0.1.107/dist/plasmic.schema.json"
}
